disnake/ext/bracord/__init__.py
disnake/ext/bracord/boilerplate.py
disnake/ext/bracord/cli/cog_init.py
disnake/ext/bracord/cli/console_commands.py
disnake/ext/bracord/cli/project_init.py
disnake/ext/bracord/entry.py
disnake/ext/bracord/utils.py
bracord-0.3.2.dist-info/entry_points.txt
bracord-0.3.2.dist-info/LICENSE
bracord-0.3.2.dist-info/WHEEL
bracord-0.3.2.dist-info/METADATA
bracord-0.3.2.dist-info/RECORD
